idEXLatch.v
module idExLatch (
    input  wire        clk,
    input  wire        rst,
    input  wire [1:0]  ctl_wb,
    input  wire [2:0]  ctl_mem,
    input  wire [3:0]  ctl_ex,
    input  wire [31:0] npc,
    input  wire [31:0] readdat1,
    input  wire [31:0] readdat2,
    input  wire [31:0] sign_ext,
    input  wire [4:0]  instr_bits_20_16,
    input  wire [4:0]  instr_bits_15_11,
    //outputs
    output reg  [1:0]  wb_out,
    output reg  [2:0]  mem_out,
    output reg  [3:0]  ctl_out,
    output reg  [31:0] npc_out,
    output reg  [31:0] readdat1_out,
    output reg  [31:0] readdat2_out,
    output reg  [31:0] sign_ext_out,
    output reg  [4:0]  instr_bits_20_16_out,
    output reg  [4:0]  instr_bits_15_11_out
);
    always @(posedge clk) begin
        if (rst) begin
            wb_out               <= 2'b0;
            mem_out              <= 3'b0;
            ctl_out              <= 4'b0;
            npc_out              <= 32'b0;
            readdat1_out         <= 32'b0;
            readdat2_out         <= 32'b0;
            sign_ext_out         <= 32'b0;
            instr_bits_20_16_out <= 5'b0;
            instr_bits_15_11_out <= 5'b0;
        end else begin
            wb_out               <= ctl_wb;
            mem_out              <= ctl_mem;
            ctl_out              <= ctl_ex;
            npc_out              <= npc;
            readdat1_out         <= readdat1;
            readdat2_out         <= readdat2;
            sign_ext_out         <= sign_ext;
            instr_bits_20_16_out <= instr_bits_20_16;
            instr_bits_15_11_out <= instr_bits_15_11;
        end
    end
endmodule

control.v
module control (
    input  wire        clk,
    input  wire        rst,
    input  wire [5:0]  opcode,
    output reg  [1:0]  wb,
    output reg  [2:0]  mem,     
    output reg  [3:0]  ex       
);
parameter RTYPE = 6'b000000; 

parameter LW = 6'b100011;
parameter SW = 6'b101011;
parameter BEQ= 6'b000100;
parameter NOP = 6'b100000;

//default values
initial begin
wb = 2'd0;
mem = 3'd0;
ex = 4'd0;
end

always @(posedge clk) begin
if (rst) begin
wb <= 6'b000000;
mem <= 6'b000000;
ex <= 6'b000000;
end


case(opcode)
RTYPE: begin
    wb<= 2'b10;
    mem<= 3'b000;
    ex<= 4'b1100;
end
LW: begin
    wb<= 2'b11;
    mem<= 3'b011;
    ex<= 4'b0001;
end

SW: begin
    wb<= 2'b00;
    mem<= 3'b001;
    ex<= 4'b0001;
end

BEQ: begin
    wb<= 2'b00;
    mem<= 3'b100;
    ex<= 4'b0010;
end

default: begin
$display ("Opcode not recognized.");
wb <= 2'd0;
mem <= 3'd0;
ex<=4'd0;
end

endcase
end
endmodule

regfile.v
module regfile (
    input  wire        clk,
    input  wire        rst,
    input  wire        regwrite,
    input  wire [4:0]  rs,          
    input  wire [4:0]  rt,          
    input  wire [4:0]  rd,          
    input  wire [31:0] writedata,   
    output reg [31:0] A_readdat1,
    output reg [31:0] B_readdat2
);
    reg [31:0] REG [0:31];    
    initial begin
    REG[0] = 'h002300AA;
    REG[1] = 'h10654321;
    REG[2] = 'h00100022;
    REG[3] = 'h8C123456;
    REG[4] = 'h8F123456;
    REG[5] = 'hAD654321;
    REG[6] = 'h60000066;
    REG[7] = 'h13012345;
    REG[8] = 'hAC654321;
    REG[9] = 'h12012345;
    end

   always @(posedge clk) begin
    if (rst)begin
        A_readdat1<= 32'h0;
        B_readdat2<= 32'h0;
    end
    else begin
        if(regwrite) begin
         REG[rd] <= writedata;    
        end
    else begin
        A_readdat1 <= REG[rs];
        B_readdat2 <= REG[rt];
        end
    end
end
endmodule

signExt.v
module signExt(
input wire [15:0] immediate,
output wire [31:0] extended
);
assign extended = {{16{immediate[15]}},immediate};  //prepend Immediate with 16 bits of the MSB
endmodule

Decode.v
module decode (
    input  wire        clk,
    input  wire        rst,
    input  wire        wb_reg_write,
    input  wire [4:0]  wb_write_reg_location,
    input  wire [31:0] mem_wb_write_data,
    input  wire [31:0] if_id_instr,
    input  wire [31:0] if_id_npc,
    //outputs
    output wire [1:0]  id_ex_wb,
    output wire [2:0]  id_ex_mem,
    output wire [3:0]  id_ex_execute,
    output wire [31:0] id_ex_npc,
    output wire [31:0] id_ex_readdat1,
    output wire [31:0] id_ex_readdat2,
    output wire [31:0] id_ex_sign_ext,
    output wire [4:0]  id_ex_instr_bits_20_16,
    output wire [4:0]  id_ex_instr_bits_15_11
);
   //internal wires
    wire [31:0] sign_ext_internal;
    wire [31:0] readdat1_internal;
    wire [31:0] readdat2_internal;
    wire [1:0]  wb_internal;
    wire [2:0]  mem_internal;
    wire [3:0]  ex_internal;

    signExt sE0 (
        .immediate(if_id_instr[15:0]),
        .extended(sign_ext_internal)
    );

    regfile rf0 (
        .clk(clk),
        .rst(rst),
        .regwrite(wb_reg_write),
        .rs(if_id_instr[25:21]),
        .rt(if_id_instr[20:16]),
        .rd(wb_write_reg_location),
        .writedata(mem_wb_write_data),
        .A_readdat1(readdat1_internal),
        .B_readdat2(readdat2_internal)
    );

    control c0 (
        .clk(clk),
        .rst(rst),
        .opcode(if_id_instr[31:26]),
        .wb(wb_internal),
        .mem(mem_internal),
        .ex(ex_internal)
    );

    idExLatch iEL0 (
        .clk(clk),
        .rst(rst),
        .ctl_wb(wb_internal),
        .ctl_mem(mem_internal),
        .ctl_ex(ex_internal),
        .npc(if_id_npc),
        .readdat1(readdat1_internal),
        .readdat2(readdat2_internal),
        .sign_ext(sign_ext_internal),
        .instr_bits_20_16(if_id_instr[20:16]),
        .instr_bits_15_11(if_id_instr[15:11]),
        .wb_out(id_ex_wb),
        .mem_out(id_ex_mem),
        .ctl_out(id_ex_execute),
        .npc_out(id_ex_npc),
        .readdat1_out(id_ex_readdat1),
        .readdat2_out(id_ex_readdat2),
        .sign_ext_out(id_ex_sign_ext),
        .instr_bits_20_16_out(id_ex_instr_bits_20_16),
        .instr_bits_15_11_out(id_ex_instr_bits_15_11)
    );

endmodule

decode_tb.v
`timescale 1ns/1ps

module decode_tb;
    reg clk_tb, rst_tb, wb_reg_write_tb;
    reg [4:0]  wb_write_reg_location_tb;
    reg [31:0] mem_wb_write_data_tb, if_id_instr_tb, if_id_npc_tb;

    wire [1:0]  id_ex_wb_tb;
    wire [2:0]  id_ex_mem_tb;
    wire [3:0]  id_ex_execute_tb;
    wire [31:0] id_ex_npc_tb, id_ex_readdat1_tb, id_ex_readdat2_tb, id_ex_sign_ext_tb;
    wire [4:0]  id_ex_instr_bits_20_16_tb, id_ex_instr_bits_15_11_tb;

    decode DUT (
        .clk(clk_tb), .rst(rst_tb), .wb_reg_write(wb_reg_write_tb),
        .wb_write_reg_location(wb_write_reg_location_tb),
        .mem_wb_write_data(mem_wb_write_data_tb),
        .if_id_instr(if_id_instr_tb), .if_id_npc(if_id_npc_tb),
        .id_ex_wb(id_ex_wb_tb), .id_ex_mem(id_ex_mem_tb),
        .id_ex_execute(id_ex_execute_tb), .id_ex_npc(id_ex_npc_tb),
        .id_ex_readdat1(id_ex_readdat1_tb), .id_ex_readdat2(id_ex_readdat2_tb),
        .id_ex_sign_ext(id_ex_sign_ext_tb),
        .id_ex_instr_bits_20_16(id_ex_instr_bits_20_16_tb),
        .id_ex_instr_bits_15_11(id_ex_instr_bits_15_11_tb)
    );

    initial begin 
        clk_tb = 0;
        forever #1 clk_tb = ~clk_tb;
    end

    initial begin
        $dumpfile("decode_tb.vcd");
        $dumpvars(0, decode_tb);
    end
initial begin
        rst_tb = 1; 
        wb_reg_write_tb = 0;
        wb_write_reg_location_tb = 5'd2; 
        mem_wb_write_data_tb = 32'h64;
        if_id_npc_tb = 32'h0000001;

        // ADD $v0, $a1,$a0
        if_id_instr_tb = 32'h00a41020;
        #2;

        rst_tb = 0; //reset disabled
        #2

        if_id_npc_tb = 32'h0000002;
        //BEQ $zero,$zero,0x8
        if_id_instr_tb = 32'h10000008;
        #2
        if_id_npc_tb = 32'h0000003;
        //LW $v0,2($a0)
        if_id_instr_tb = 32'h8c820002;
        #2

        if_id_npc_tb = 32'h0000004;
        //SW $v0, 2($a0)
        if_id_instr_tb = 32'hac820002;
        #2

        if_id_npc_tb = 32'h0000005;
        wb_reg_write_tb = 1;
        #2
        //ADD $v0, $v0, $v0
        if_id_instr_tb = 32'h00421020;

        if_id_npc_tb = 32'h00421020;
        wb_reg_write_tb = 0;
        #2
        #2
        $display("Decode Complete");
        $finish;
    end
endmodule

decode_tb.vcd
$date
	Fri Mar 20 19:31:18 2026
$end
$version
	Icarus Verilog
$end
$timescale
	1ps
$end
$scope module decode_tb $end
$var wire 2 ! id_ex_wb_tb [1:0] $end
$var wire 32 " id_ex_sign_ext_tb [31:0] $end
$var wire 32 # id_ex_readdat2_tb [31:0] $end
$var wire 32 $ id_ex_readdat1_tb [31:0] $end
$var wire 32 % id_ex_npc_tb [31:0] $end
$var wire 3 & id_ex_mem_tb [2:0] $end
$var wire 5 ' id_ex_instr_bits_20_16_tb [4:0] $end
$var wire 5 ( id_ex_instr_bits_15_11_tb [4:0] $end
$var wire 4 ) id_ex_execute_tb [3:0] $end
$var reg 1 * clk_tb $end
$var reg 32 + if_id_instr_tb [31:0] $end
$var reg 32 , if_id_npc_tb [31:0] $end
$var reg 32 - mem_wb_write_data_tb [31:0] $end
$var reg 1 . rst_tb $end
$var reg 1 / wb_reg_write_tb $end
$var reg 5 0 wb_write_reg_location_tb [4:0] $end
$scope module DUT $end
$var wire 1 * clk $end
$var wire 32 1 if_id_instr [31:0] $end
$var wire 32 2 if_id_npc [31:0] $end
$var wire 32 3 mem_wb_write_data [31:0] $end
$var wire 1 . rst $end
$var wire 1 / wb_reg_write $end
$var wire 5 4 wb_write_reg_location [4:0] $end
$var wire 2 5 wb_internal [1:0] $end
$var wire 32 6 sign_ext_internal [31:0] $end
$var wire 32 7 readdat2_internal [31:0] $end
$var wire 32 8 readdat1_internal [31:0] $end
$var wire 3 9 mem_internal [2:0] $end
$var wire 2 : id_ex_wb [1:0] $end
$var wire 32 ; id_ex_sign_ext [31:0] $end
$var wire 32 < id_ex_readdat2 [31:0] $end
$var wire 32 = id_ex_readdat1 [31:0] $end
$var wire 32 > id_ex_npc [31:0] $end
$var wire 3 ? id_ex_mem [2:0] $end
$var wire 5 @ id_ex_instr_bits_20_16 [4:0] $end
$var wire 5 A id_ex_instr_bits_15_11 [4:0] $end
$var wire 4 B id_ex_execute [3:0] $end
$var wire 4 C ex_internal [3:0] $end
$scope module c0 $end
$var wire 1 * clk $end
$var wire 6 D opcode [5:0] $end
$var wire 1 . rst $end
$var parameter 6 E BEQ $end
$var parameter 6 F LW $end
$var parameter 6 G NOP $end
$var parameter 6 H RTYPE $end
$var parameter 6 I SW $end
$var reg 4 J ex [3:0] $end
$var reg 3 K mem [2:0] $end
$var reg 2 L wb [1:0] $end
$upscope $end
$scope module iEL0 $end
$var wire 1 * clk $end
$var wire 4 M ctl_ex [3:0] $end
$var wire 3 N ctl_mem [2:0] $end
$var wire 2 O ctl_wb [1:0] $end
$var wire 5 P instr_bits_15_11 [4:0] $end
$var wire 5 Q instr_bits_20_16 [4:0] $end
$var wire 32 R npc [31:0] $end
$var wire 1 . rst $end
$var wire 32 S sign_ext [31:0] $end
$var wire 32 T readdat2 [31:0] $end
$var wire 32 U readdat1 [31:0] $end
$var reg 4 V ctl_out [3:0] $end
$var reg 5 W instr_bits_15_11_out [4:0] $end
$var reg 5 X instr_bits_20_16_out [4:0] $end
$var reg 3 Y mem_out [2:0] $end
$var reg 32 Z npc_out [31:0] $end
$var reg 32 [ readdat1_out [31:0] $end
$var reg 32 \ readdat2_out [31:0] $end
$var reg 32 ] sign_ext_out [31:0] $end
$var reg 2 ^ wb_out [1:0] $end
$upscope $end
$scope module rf0 $end
$var wire 1 * clk $end
$var wire 5 _ rd [4:0] $end
$var wire 1 / regwrite $end
$var wire 5 ` rs [4:0] $end
$var wire 1 . rst $end
$var wire 5 a rt [4:0] $end
$var wire 32 b writedata [31:0] $end
$var reg 32 c A_readdat1 [31:0] $end
$var reg 32 d B_readdat2 [31:0] $end
$upscope $end
$scope module sE0 $end
$var wire 16 e immediate [15:0] $end
$var wire 32 f extended [31:0] $end
$upscope $end
$upscope $end
$upscope $end
$enddefinitions $end
$comment Show the parameter values. $end
$dumpall
b101011 I
b0 H
b100000 G
b100011 F
b100 E
$end
#0
$dumpvars
b1000000100000 f
b1000000100000 e
bx d
bx c
b1100100 b
b100 a
b101 `
b10 _
bx ^
bx ]
bx \
bx [
bx Z
bx Y
bx X
bx W
bx V
bx U
bx T
b1000000100000 S
b1 R
b100 Q
b10 P
b0 O
b0 N
b0 M
b0 L
b0 K
b0 J
b0 D
b0 C
bx B
bx A
bx @
bx ?
bx >
bx =
bx <
bx ;
bx :
b0 9
bx 8
bx 7
b1000000100000 6
b0 5
b10 4
b1100100 3
b1 2
b101001000001000000100000 1
b10 0
0/
1.
b1100100 -
b1 ,
b101001000001000000100000 +
0*
bx )
bx (
bx '
bx &
bx %
bx $
bx #
bx "
bx !
$end
#1000
b0 7
b0 T
b0 d
b0 8
b0 U
b0 c
b1100 C
b1100 J
b1100 M
b10 5
b10 L
b10 O
b0 (
b0 A
b0 W
b0 '
b0 @
b0 X
b0 "
b0 ;
b0 ]
b0 #
b0 <
b0 \
b0 $
b0 =
b0 [
b0 %
b0 >
b0 Z
b0 )
b0 B
b0 V
b0 &
b0 ?
b0 Y
b0 !
b0 :
b0 ^
1*
#2000
0*
0.
#3000
b10 (
b10 A
b10 W
b100 '
b100 @
b100 X
b1000000100000 "
b1000000100000 ;
b1000000100000 ]
b1 %
b1 >
b1 Z
b1100 )
b1100 B
b1100 V
b10 !
b10 :
b10 ^
b10001111000100100011010001010110 7
b10001111000100100011010001010110 T
b10001111000100100011010001010110 d
b10101101011001010100001100100001 8
b10101101011001010100001100100001 U
b10101101011001010100001100100001 c
1*
#4000
b1000 6
b1000 S
b1000 f
b1000 e
b0 `
b0 a
b100 D
b0 Q
b0 P
0*
b10000000000000000000000001000 +
b10000000000000000000000001000 1
b10 ,
b10 2
b10 R
#5000
b1000110000000010101010 7
b1000110000000010101010 T
b1000110000000010101010 d
b1000110000000010101010 8
b1000110000000010101010 U
b1000110000000010101010 c
b10 C
b10 J
b10 M
b100 9
b100 K
b100 N
b0 5
b0 L
b0 O
b0 (
b0 A
b0 W
b0 '
b0 @
b0 X
b1000 "
b1000 ;
b1000 ]
b10001111000100100011010001010110 #
b10001111000100100011010001010110 <
b10001111000100100011010001010110 \
b10101101011001010100001100100001 $
b10101101011001010100001100100001 =
b10101101011001010100001100100001 [
b10 %
b10 >
b10 Z
1*
#6000
b10 6
b10 S
b10 f
b10 e
b100 `
b10 a
b100011 D
b10 Q
0*
b10001100100000100000000000000010 +
b10001100100000100000000000000010 1
b11 ,
b11 2
b11 R
#7000
b10 '
b10 @
b10 X
b10 "
b10 ;
b10 ]
b1000110000000010101010 #
b1000110000000010101010 <
b1000110000000010101010 \
b1000110000000010101010 $
b1000110000000010101010 =
b1000110000000010101010 [
b11 %
b11 >
b11 Z
b10 )
b10 B
b10 V
b100 &
b100 ?
b100 Y
b0 !
b0 :
b0 ^
b1 C
b1 J
b1 M
b11 9
b11 K
b11 N
b11 5
b11 L
b11 O
b100000000000000100010 7
b100000000000000100010 T
b100000000000000100010 d
b10001111000100100011010001010110 8
b10001111000100100011010001010110 U
b10001111000100100011010001010110 c
1*
#8000
b101011 D
0*
b10101100100000100000000000000010 +
b10101100100000100000000000000010 1
b100 ,
b100 2
b100 R
#9000
b1 9
b1 K
b1 N
b0 5
b0 L
b0 O
b100000000000000100010 #
b100000000000000100010 <
b100000000000000100010 \
b10001111000100100011010001010110 $
b10001111000100100011010001010110 =
b10001111000100100011010001010110 [
b100 %
b100 >
b100 Z
b1 )
b1 B
b1 V
b11 &
b11 ?
b11 Y
b11 !
b11 :
b11 ^
1*
#10000
0*
1/
b101 ,
b101 2
b101 R
#11000
b101 %
b101 >
b101 Z
b1 &
b1 ?
b1 Y
b0 !
b0 :
b0 ^
1*
#12000
b1000000100000 6
b1000000100000 S
b1000000100000 f
b1000000100000 e
b10 `
b0 D
b10 P
0*
0/
b10000100001000000100000 ,
b10000100001000000100000 2
b10000100001000000100000 R
b10000100001000000100000 +
b10000100001000000100000 1
#13000
b1100100 7
b1100100 T
b1100100 d
b1100100 8
b1100100 U
b1100100 c
b1100 C
b1100 J
b1100 M
b0 9
b0 K
b0 N
b10 5
b10 L
b10 O
b10 (
b10 A
b10 W
b1000000100000 "
b1000000100000 ;
b1000000100000 ]
b10000100001000000100000 %
b10000100001000000100000 >
b10000100001000000100000 Z
1*
#14000
0*
#15000
b1100100 #
b1100100 <
b1100100 \
b1100100 $
b1100100 =
b1100100 [
b1100 )
b1100 B
b1100 V
b0 &
b0 ?
b0 Y
b10 !
b10 :
b10 ^
1*
