idEXLatch.v
module idExLatch (
    input  wire        clk,
    input  wire        rst,
    // Control signals in
    input  wire [1:0]  ctl_wb,
    input  wire [2:0]  ctl_mem,
    input  wire [3:0]  ctl_ex,
    // Data in
    input  wire [31:0] npc,
    input  wire [31:0] readdat1,
    input  wire [31:0] readdat2,
    input  wire [31:0] sign_ext,
    input  wire [4:0]  instr_bits_20_16,
    input  wire [4:0]  instr_bits_15_11,
    // Outputs (all reg — latched on clock edge)
    output reg  [1:0]  wb_out,
    output reg  [2:0]  mem_out,
    output reg  [3:0]  ctl_out,
    output reg  [31:0] npc_out,
    output reg  [31:0] readdat1_out,
    output reg  [31:0] readdat2_out,
    output reg  [31:0] sign_ext_out,
    output reg  [4:0]  instr_bits_20_16_out,
    output reg  [4:0]  instr_bits_15_11_out
);
    always @(posedge clk or negedge rst) begin
        if (!rst) begin
            wb_out               <= 2'b0;
            mem_out              <= 3'b0;
            ctl_out              <= 4'b0;
            npc_out              <= 32'b0;
            readdat1_out         <= 32'b0;
            readdat2_out         <= 32'b0;
            sign_ext_out         <= 32'b0;
            instr_bits_20_16_out <= 5'b0;
            instr_bits_15_11_out <= 5'b0;
        end else begin
            wb_out               <= ctl_wb;
            mem_out              <= ctl_mem;
            ctl_out              <= ctl_ex;
            npc_out              <= npc;
            readdat1_out         <= readdat1;
            readdat2_out         <= readdat2;
            sign_ext_out         <= sign_ext;
            instr_bits_20_16_out <= instr_bits_20_16;
            instr_bits_15_11_out <= instr_bits_15_11;
        end
    end
endmodule

control.v
module control (
    input  wire        clk,
    input  wire        rst,
    input  wire [5:0]  opcode,
    output reg  [1:0]  wb,       // [1]=MemToReg, [0]=RegWrite
    output reg  [2:0]  mem,      // [2]=Branch,   [1]=MemRead, [0]=MemWrite
    output reg  [3:0]  ex        // [3:2]=ALUOp,  [1]=ALUSrc,  [0]=RegDst
);
    always @(*) begin
        case (opcode)
            6'b000000: begin  // R-format
                wb  = 2'b01;  // RegWrite=1, MemToReg=0
                mem = 3'b000; // Branch=0, MemRead=0, MemWrite=0
                ex  = 4'b1001;// ALUOp=10, ALUSrc=0, RegDst=1
            end
            6'b100011: begin  // LW
                wb  = 2'b11;  // RegWrite=1, MemToReg=1
                mem = 3'b010; // Branch=0, MemRead=1, MemWrite=0
                ex  = 4'b0010;// ALUOp=00, ALUSrc=1, RegDst=0
            end
            6'b101011: begin  // SW
                wb  = 2'b00;  // RegWrite=0, MemToReg=X
                mem = 3'b001; // Branch=0, MemRead=0, MemWrite=1
                ex  = 4'b0010;// ALUOp=00, ALUSrc=1, RegDst=X
            end
            6'b000100: begin  // BEQ
                wb  = 2'b00;  // RegWrite=0
                mem = 3'b100; // Branch=1, MemRead=0, MemWrite=0
                ex  = 4'b0100;// ALUOp=01, ALUSrc=0, RegDst=X
            end
            default: begin
                wb  = 2'b00;
                mem = 3'b000;
                ex  = 4'b0000;
            end
        endcase
    end
endmodule

regfile.v
module regfile (
    input  wire        clk,
    input  wire        rst,
    input  wire        regwrite,
    input  wire [4:0]  rs,          // Read Reg1 -> instruction[25:21]
    input  wire [4:0]  rt,          // Read Reg2 -> instruction[20:16]
    input  wire [4:0]  rd,          // Write Reg  -> from Mem/WB latch
    input  wire [31:0] writedata,   // Write Data -> from WB Mux
    output wire [31:0] A_readdat1,
    output wire [31:0] B_readdat2
);
    reg [31:0] registers [0:31];    // 32 x 32-bit registers
    integer i;

    // Synchronous write, async reset
    always @(posedge clk or negedge rst) begin
        if (!rst) begin
            for (i = 0; i < 32; i = i + 1)
                registers[i] <= 32'b0;
        end else if (regwrite && rd != 5'b0) begin
            // $0 is hardwired to 0 in MIPS, so guard against writing it
            registers[rd] <= writedata;
        end
    end

    // Asynchronous (combinational) reads
    assign A_readdat1 = registers[rs];
    assign B_readdat2 = registers[rt];
endmodule

signExt.v
module signExt(
input wire [15:0] immediate,
output wire [31:0] extended
);
assign extended = {{16{immediate[15]}}, immediate};
endmodule

Decode.v
module decode (
    input  wire        clk,
    input  wire        rst,
    input  wire        wb_reg_write,
    input  wire [4:0]  wb_write_reg_location,
    input  wire [31:0] mem_wb_write_data,
    input  wire [31:0] if_id_instr,
    input  wire [31:0] if_id_npc,
    output wire [1:0]  id_ex_wb,
    output wire [2:0]  id_ex_mem,
    output wire [3:0]  id_ex_execute,
    output wire [31:0] id_ex_npc,
    output wire [31:0] id_ex_readdat1,
    output wire [31:0] id_ex_readdat2,
    output wire [31:0] id_ex_sign_ext,
    output wire [4:0]  id_ex_instr_bits_20_16,
    output wire [4:0]  id_ex_instr_bits_15_11
);
    // Internal wires (combinational outputs from submodules)
    wire [31:0] sign_ext_internal;
    wire [31:0] readdat1_internal;
    wire [31:0] readdat2_internal;
    wire [1:0]  wb_internal;
    wire [2:0]  mem_internal;
    wire [3:0]  ex_internal;

    signExt sE0 (
        .immediate(if_id_instr[15:0]),
        .extended(sign_ext_internal)
    );

    regfile rf0 (
        .clk(clk),
        .rst(rst),
        .regwrite(wb_reg_write),
        .rs(if_id_instr[25:21]),
        .rt(if_id_instr[20:16]),
        .rd(wb_write_reg_location),
        .writedata(mem_wb_write_data),
        .A_readdat1(readdat1_internal),
        .B_readdat2(readdat2_internal)
    );

    control c0 (
        .clk(clk),
        .rst(rst),
        .opcode(if_id_instr[31:26]),
        .wb(wb_internal),
        .mem(mem_internal),
        .ex(ex_internal)
    );

    idExLatch iEL0 (
        .clk(clk),
        .rst(rst),
        .ctl_wb(wb_internal),
        .ctl_mem(mem_internal),
        .ctl_ex(ex_internal),
        .npc(if_id_npc),
        .readdat1(readdat1_internal),
        .readdat2(readdat2_internal),
        .sign_ext(sign_ext_internal),
        .instr_bits_20_16(if_id_instr[20:16]),
        .instr_bits_15_11(if_id_instr[15:11]),
        .wb_out(id_ex_wb),
        .mem_out(id_ex_mem),
        .ctl_out(id_ex_execute),
        .npc_out(id_ex_npc),
        .readdat1_out(id_ex_readdat1),
        .readdat2_out(id_ex_readdat2),
        .sign_ext_out(id_ex_sign_ext),
        .instr_bits_20_16_out(id_ex_instr_bits_20_16),
        .instr_bits_15_11_out(id_ex_instr_bits_15_11)
    );

endmodule

decode_tb.v
`timescale 1ns/1ps

module decode_tb;
    reg clk, rst, wb_reg_write;
    reg [4:0]  wb_write_reg_location;
    reg [31:0] mem_wb_write_data, if_id_instr, if_id_npc;

    wire [1:0]  id_ex_wb;
    wire [2:0]  id_ex_mem;
    wire [3:0]  id_ex_execute;
    wire [31:0] id_ex_npc, id_ex_readdat1, id_ex_readdat2, id_ex_sign_ext;
    wire [4:0]  id_ex_instr_bits_20_16, id_ex_instr_bits_15_11;

    decode DUT (
        .clk(clk), .rst(rst), .wb_reg_write(wb_reg_write),
        .wb_write_reg_location(wb_write_reg_location),
        .mem_wb_write_data(mem_wb_write_data),
        .if_id_instr(if_id_instr), .if_id_npc(if_id_npc),
        .id_ex_wb(id_ex_wb), .id_ex_mem(id_ex_mem),
        .id_ex_execute(id_ex_execute), .id_ex_npc(id_ex_npc),
        .id_ex_readdat1(id_ex_readdat1), .id_ex_readdat2(id_ex_readdat2),
        .id_ex_sign_ext(id_ex_sign_ext),
        .id_ex_instr_bits_20_16(id_ex_instr_bits_20_16),
        .id_ex_instr_bits_15_11(id_ex_instr_bits_15_11)
    );

    always #5 clk = ~clk;

    initial begin
        $dumpfile("decode_tb.vcd");
        $dumpvars(0, decode_tb);

        clk = 0; rst = 1; wb_reg_write = 0;
        wb_write_reg_location = 0; mem_wb_write_data = 0;
        if_id_instr = 0; if_id_npc = 32'h00000004;
        #10 rst = 0;

        // Test 1: R-format ADD ($3 = $1 + $2)
        // opcode=000000, rs=$1, rt=$2, rd=$3
        if_id_instr = 32'b000000_00001_00010_00011_00000_100000;
        #10;

        // Test 2: Write $5 = 0xDEADBEEF via WB writeback, then read it
        wb_reg_write = 1;
        wb_write_reg_location = 5;
        mem_wb_write_data = 32'hDEADBEEF;
        #10 wb_reg_write = 0;

        // Read back $5 via rs field
        if_id_instr = 32'b000000_00101_00000_00000_00000_100000;
        #10;

        // Test 3: LW  (opcode=100011)
        if_id_instr = 32'b100011_00001_00010_1111111111111111; // offset=-1
        #10;

        // Test 4: SW (opcode=101011)
        if_id_instr = 32'b101011_00001_00010_0000000000001000;
        #10;

        // Test 5: BEQ (opcode=000100)
        if_id_instr = 32'b000100_00001_00010_0000000000000101;
        #10;

        $finish;
    end
endmodule

decode_tb.vcd
$date
	Wed Mar 18 19:58:31 2026
$end
$version
	Icarus Verilog
$end
$timescale
	1ps
$end
$scope module decode_tb $end
$var wire 2 ! id_ex_wb [1:0] $end
$var wire 32 " id_ex_sign_ext [31:0] $end
$var wire 32 # id_ex_readdat2 [31:0] $end
$var wire 32 $ id_ex_readdat1 [31:0] $end
$var wire 32 % id_ex_npc [31:0] $end
$var wire 3 & id_ex_mem [2:0] $end
$var wire 5 ' id_ex_instr_bits_20_16 [4:0] $end
$var wire 5 ( id_ex_instr_bits_15_11 [4:0] $end
$var wire 4 ) id_ex_execute [3:0] $end
$var reg 1 * clk $end
$var reg 32 + if_id_instr [31:0] $end
$var reg 32 , if_id_npc [31:0] $end
$var reg 32 - mem_wb_write_data [31:0] $end
$var reg 1 . rst $end
$var reg 1 / wb_reg_write $end
$var reg 5 0 wb_write_reg_location [4:0] $end
$scope module DUT $end
$var wire 1 * clk $end
$var wire 32 1 if_id_instr [31:0] $end
$var wire 32 2 if_id_npc [31:0] $end
$var wire 32 3 mem_wb_write_data [31:0] $end
$var wire 1 . rst $end
$var wire 1 / wb_reg_write $end
$var wire 5 4 wb_write_reg_location [4:0] $end
$var wire 2 5 wb_internal [1:0] $end
$var wire 32 6 sign_ext_internal [31:0] $end
$var wire 32 7 readdat2_internal [31:0] $end
$var wire 32 8 readdat1_internal [31:0] $end
$var wire 3 9 mem_internal [2:0] $end
$var wire 2 : id_ex_wb [1:0] $end
$var wire 32 ; id_ex_sign_ext [31:0] $end
$var wire 32 < id_ex_readdat2 [31:0] $end
$var wire 32 = id_ex_readdat1 [31:0] $end
$var wire 32 > id_ex_npc [31:0] $end
$var wire 3 ? id_ex_mem [2:0] $end
$var wire 5 @ id_ex_instr_bits_20_16 [4:0] $end
$var wire 5 A id_ex_instr_bits_15_11 [4:0] $end
$var wire 4 B id_ex_execute [3:0] $end
$var wire 4 C ex_internal [3:0] $end
$scope module c0 $end
$var wire 1 * clk $end
$var wire 6 D opcode [5:0] $end
$var wire 1 . rst $end
$var reg 4 E ex [3:0] $end
$var reg 3 F mem [2:0] $end
$var reg 2 G wb [1:0] $end
$upscope $end
$scope module iEL0 $end
$var wire 1 * clk $end
$var wire 4 H ctl_ex [3:0] $end
$var wire 3 I ctl_mem [2:0] $end
$var wire 2 J ctl_wb [1:0] $end
$var wire 5 K instr_bits_15_11 [4:0] $end
$var wire 5 L instr_bits_20_16 [4:0] $end
$var wire 32 M npc [31:0] $end
$var wire 1 . rst $end
$var wire 32 N sign_ext [31:0] $end
$var wire 32 O readdat2 [31:0] $end
$var wire 32 P readdat1 [31:0] $end
$var reg 4 Q ctl_out [3:0] $end
$var reg 5 R instr_bits_15_11_out [4:0] $end
$var reg 5 S instr_bits_20_16_out [4:0] $end
$var reg 3 T mem_out [2:0] $end
$var reg 32 U npc_out [31:0] $end
$var reg 32 V readdat1_out [31:0] $end
$var reg 32 W readdat2_out [31:0] $end
$var reg 32 X sign_ext_out [31:0] $end
$var reg 2 Y wb_out [1:0] $end
$upscope $end
$scope module rf0 $end
$var wire 32 Z A_readdat1 [31:0] $end
$var wire 32 [ B_readdat2 [31:0] $end
$var wire 1 * clk $end
$var wire 5 \ rd [4:0] $end
$var wire 1 / regwrite $end
$var wire 5 ] rs [4:0] $end
$var wire 1 . rst $end
$var wire 5 ^ rt [4:0] $end
$var wire 32 _ writedata [31:0] $end
$var integer 32 ` i [31:0] $end
$upscope $end
$scope module sE0 $end
$var wire 16 a immediate [15:0] $end
$var wire 32 b extended [31:0] $end
$upscope $end
$upscope $end
$upscope $end
$enddefinitions $end
$comment Show the parameter values. $end
$dumpall
$end
#0
$dumpvars
b0 b
b0 a
bx `
b0 _
b0 ^
b0 ]
b0 \
bx [
bx Z
bx Y
bx X
bx W
bx V
bx U
bx T
bx S
bx R
bx Q
bx P
bx O
b0 N
b100 M
b0 L
b0 K
b1 J
b0 I
b1001 H
b1 G
b0 F
b1001 E
b0 D
b1001 C
bx B
bx A
bx @
bx ?
bx >
bx =
bx <
bx ;
bx :
b0 9
bx 8
bx 7
b0 6
b1 5
b0 4
b0 3
b100 2
b0 1
b0 0
0/
1.
b0 -
b100 ,
b0 +
0*
bx )
bx (
bx '
bx &
bx %
bx $
bx #
bx "
bx !
$end
#5000
b0 (
b0 A
b0 R
b0 '
b0 @
b0 S
b0 "
b0 ;
b0 X
b100 %
b100 >
b100 U
b1001 )
b1001 B
b1001 Q
b0 &
b0 ?
b0 T
b1 !
b1 :
b1 Y
1*
#10000
b0 #
b0 <
b0 W
b0 $
b0 =
b0 V
b0 %
b0 >
b0 U
b0 )
b0 B
b0 Q
b0 !
b0 :
b0 Y
b0 7
b0 O
b0 [
b0 8
b0 P
b0 Z
b1100000100000 6
b1100000100000 N
b1100000100000 b
b1100000100000 a
b1 ]
b10 ^
b10 L
b11 K
b100000 `
0*
b1000100001100000100000 +
b1000100001100000100000 1
0.
#15000
b100000 `
1*
#20000
0*
b11011110101011011011111011101111 -
b11011110101011011011111011101111 3
b11011110101011011011111011101111 _
b101 0
b101 4
b101 \
1/
#25000
b100000 `
1*
#30000
b100000 6
b100000 N
b100000 b
b100000 a
b101 ]
b0 ^
b0 L
b0 K
0*
b101000000000000000100000 +
b101000000000000000100000 1
0/
#35000
b100000 `
1*
#40000
b10 C
b10 E
b10 H
b10 9
b10 F
b10 I
b11 5
b11 G
b11 J
b11111111111111111111111111111111 6
b11111111111111111111111111111111 N
b11111111111111111111111111111111 b
b1111111111111111 a
b1 ]
b10 ^
b100011 D
b10 L
b11111 K
0*
b10001100001000101111111111111111 +
b10001100001000101111111111111111 1
#45000
b100000 `
1*
#50000
b1 9
b1 F
b1 I
b0 5
b0 G
b0 J
b1000 6
b1000 N
b1000 b
b1000 a
b101011 D
b0 K
0*
b10101100001000100000000000001000 +
b10101100001000100000000000001000 1
#55000
b100000 `
1*
#60000
b100 C
b100 E
b100 H
b100 9
b100 F
b100 I
b101 6
b101 N
b101 b
b101 a
b100 D
0*
b10000001000100000000000000101 +
b10000001000100000000000000101 1
#65000
b100000 `
1*
